nlnormaliz/__init__.py
nlnormaliz/__main__.py
nlnormaliz/normaliz.py
nlnormaliz-0.0.4.dist-info/DESCRIPTION.rst
nlnormaliz-0.0.4.dist-info/METADATA
nlnormaliz-0.0.4.dist-info/RECORD
nlnormaliz-0.0.4.dist-info/WHEEL
nlnormaliz-0.0.4.dist-info/entry_points.txt
nlnormaliz-0.0.4.dist-info/metadata.json
nlnormaliz-0.0.4.dist-info/top_level.txt
