Metadata-Version: 2.0
Name: nlnormaliz
Version: 0.0.4
Summary: Natural language normalizer for documents in Python
Home-page: https://github.com/raviqqe/nlnormaliz.py/
Author: Yota Toyama
Author-email: raviqqe@gmail.com
License: Public Domain
Platform: UNKNOWN
Classifier: Development Status :: 3 - Alpha
Classifier: Intended Audience :: Developers
Classifier: License :: Public Domain
Classifier: Natural Language :: English
Classifier: Natural Language :: Japanese
Classifier: Programming Language :: Python :: 3.4
Classifier: Programming Language :: Python :: 3.5
Classifier: Programming Language :: Python :: 3.6
Classifier: Topic :: Text Processing :: Linguistic
Requires-Dist: iso639
Requires-Dist: langdetect
Requires-Dist: neologdn
